csvw_functions/__init__.py
csvw_functions/csvw_functions.py
csvw_functions/_old/csvw_functions.py
csvw_functions-0.0.0.dist-info/LICENSE
csvw_functions-0.0.0.dist-info/METADATA
csvw_functions-0.0.0.dist-info/WHEEL
csvw_functions-0.0.0.dist-info/top_level.txt
csvw_functions-0.0.0.dist-info/RECORD
