Metadata-Version: 2.1
Name: csvw_functions
Version: 0.0.0
Summary: Python functions for working with CSV on the Web datasets
Author-email: Steven Firth <s.k.firth@lboro.ac.uk>
Project-URL: Homepage, https://github.com/stevenkfirth/csvw_functions
Project-URL: Issues, https://github.com/stevenkfirth/csvw_functions/issues
Classifier: Programming Language :: Python :: 3
Classifier: License :: OSI Approved :: MIT License
Classifier: Operating System :: OS Independent
Requires-Python: >=3.6
License-File: LICENSE
Requires-Dist: requests >=2.31.0
Requires-Dist: hyperlink >=21.0.0
Requires-Dist: uritemplate >=4.1.1
Requires-Dist: langcodes >=3.3.0
Requires-Dist: python-dateutil >=2.8.2
